atmdb/__init__.py
atmdb/client.py
atmdb/core.py
atmdb/models.py
atmdb/utils.py
atmdb-0.2.3.dist-info/DESCRIPTION.rst
atmdb-0.2.3.dist-info/METADATA
atmdb-0.2.3.dist-info/RECORD
atmdb-0.2.3.dist-info/WHEEL
atmdb-0.2.3.dist-info/metadata.json
atmdb-0.2.3.dist-info/top_level.txt
