Metadata-Version: 2.0
Name: atmdb
Version: 0.2.3
Summary: Asynchronous API wrapper for TMDb (https://www.themoviedb.org/).
Home-page: http://github.com/textbook/atmdb/
Author: Jonathan Sharpe
Author-email: mail@jonrshar.pe
License: License :: OSI Approved :: ISC License (ISCL)
Platform: any
Classifier: Development Status :: 3 - Alpha
Classifier: Intended Audience :: Developers
Classifier: Natural Language :: English
Classifier: Operating System :: OS Independent
Classifier: Programming Language :: Python :: 3.5
Classifier: Programming Language :: Python :: 3 :: Only
Requires-Dist: aiohttp
Requires-Dist: python-dateutil
